ska/__init__.py
ska/base.py
ska/defaults.py
ska/error_codes.py
ska/exceptions.py
ska/generate_signed_url.py
ska/gettext.py
ska/helpers.py
ska/shortcuts.py
ska/utils.py
ska/versus.py
ska/contrib/__init__.py
ska/contrib/django/__init__.py
ska/contrib/django/ska/__init__.py
ska/contrib/django/ska/admin.py
ska/contrib/django/ska/apps.py
ska/contrib/django/ska/conf.py
ska/contrib/django/ska/decorators.py
ska/contrib/django/ska/defaults.py
ska/contrib/django/ska/http.py
ska/contrib/django/ska/models.py
ska/contrib/django/ska/settings.py
ska/contrib/django/ska/utils.py
ska/contrib/django/ska/backends/__init__.py
ska/contrib/django/ska/backends/base.py
ska/contrib/django/ska/backends/constance_backend.py
ska/contrib/django/ska/backends/default_backends.py
ska/contrib/django/ska/integration/__init__.py
ska/contrib/django/ska/integration/constance_integration/__init__.py
ska/contrib/django/ska/integration/constance_integration/templatetags/__init__.py
ska/contrib/django/ska/integration/constance_integration/templatetags/ska_constance_tags.py
ska/contrib/django/ska/integration/drf/__init__.py
ska/contrib/django/ska/integration/drf/permissions/__init__.py
ska/contrib/django/ska/integration/drf/permissions/base.py
ska/contrib/django/ska/integration/drf/permissions/constance_permissions.py
ska/contrib/django/ska/integration/drf/permissions/default_permissions.py
ska/contrib/django/ska/integration/drf/urls/__init__.py
ska/contrib/django/ska/integration/drf/urls/jwt_token.py
ska/contrib/django/ska/integration/drf/views/__init__.py
ska/contrib/django/ska/integration/drf/views/jwt_token.py
ska/contrib/django/ska/locale/hy/LC_MESSAGES/django.mo
ska/contrib/django/ska/locale/hy/LC_MESSAGES/django.po
ska/contrib/django/ska/locale/nl/LC_MESSAGES/django.mo
ska/contrib/django/ska/locale/nl/LC_MESSAGES/django.po
ska/contrib/django/ska/locale/ru/LC_MESSAGES/django.mo
ska/contrib/django/ska/locale/ru/LC_MESSAGES/django.po
ska/contrib/django/ska/management/__init__.py
ska-1.11.1.dist-info/licenses/LICENSE_GPL2.0.txt
ska-1.11.1.dist-info/licenses/LICENSE_LGPL_2.1.txt
ska-1.11.1.dist-info/METADATA
ska-1.11.1.dist-info/WHEEL
ska-1.11.1.dist-info/entry_points.txt
ska-1.11.1.dist-info/top_level.txt
ska-1.11.1.dist-info/RECORD
