Metadata-Version: 2.4
Name: ska
Version: 1.11.1
Summary: Sign- and validate- data (dictionaries, strings) using symmetric-key algorithm.
Author-email: Artur Barseghyan <artur.barseghyan@gmail.com>
License-Expression: GPL-2.0-only OR LGPL-2.1-or-later
Project-URL: Homepage, https://github.com/barseghyanartur/ska
Project-URL: Repository, https://github.com/barseghyanartur/ska
Project-URL: Issues, https://github.com/barseghyanartur/ska/issues
Project-URL: Documentation, https://ska.readthedocs.io/
Project-URL: Changelog, https://ska.readthedocs.io/en/latest/changelog.html
Keywords: sign data,sign (HTTP) request,symmetric-key algorithm encryption,sign URL,python,django,password-less login django,password-less authentication backend django
Classifier: Programming Language :: Python
Classifier: Programming Language :: Python :: 3
Classifier: Programming Language :: Python :: 3.9
Classifier: Programming Language :: Python :: 3.10
Classifier: Programming Language :: Python :: 3.11
Classifier: Programming Language :: Python :: 3.12
Classifier: Programming Language :: Python :: 3.13
Classifier: Topic :: Security :: Cryptography
Classifier: Environment :: Web Environment
Classifier: Intended Audience :: Developers
Classifier: Operating System :: OS Independent
Classifier: Development Status :: 5 - Production/Stable
License-File: LICENSE_GPL2.0.txt
License-File: LICENSE_LGPL_2.1.txt
Provides-Extra: all
Requires-Dist: ska[build,dev,django,django-constance,djangorestframework,docs,drf-jwt,test]; extra == "all"
Provides-Extra: common
Requires-Dist: ska[build,dev,docs,test]; extra == "common"
Provides-Extra: django
Requires-Dist: django-nine>=0.2.4; extra == "django"
Provides-Extra: django-constance
Requires-Dist: django-constance; extra == "django-constance"
Provides-Extra: djangorestframework
Requires-Dist: djangorestframework; extra == "djangorestframework"
Provides-Extra: drf-jwt
Requires-Dist: drf-jwt; extra == "drf-jwt"
Provides-Extra: dev
Requires-Dist: detect-secrets; extra == "dev"
Requires-Dist: doc8; extra == "dev"
Requires-Dist: ipython; extra == "dev"
Requires-Dist: mypy; extra == "dev"
Requires-Dist: pydoclint; extra == "dev"
Requires-Dist: ruff; extra == "dev"
Requires-Dist: uv; extra == "dev"
Provides-Extra: test
Requires-Dist: fake.py; extra == "test"
Requires-Dist: pytest; extra == "test"
Requires-Dist: pytest-codeblock; extra == "test"
Requires-Dist: pytest-django; extra == "test"
Requires-Dist: mock; extra == "test"
Requires-Dist: beautifulsoup4; extra == "test"
Requires-Dist: soupsieve; extra == "test"
Requires-Dist: coverage; extra == "test"
Provides-Extra: docs
Requires-Dist: sphinx<6.0; extra == "docs"
Requires-Dist: sphinx-autobuild; extra == "docs"
Requires-Dist: sphinx-rtd-theme>=1.3.0; extra == "docs"
Requires-Dist: sphinx-no-pragma; extra == "docs"
Provides-Extra: build
Requires-Dist: build; extra == "build"
Requires-Dist: twine; extra == "build"
Requires-Dist: wheel; extra == "build"
Dynamic: license-file
